chlorine/__init__.py
chlorine/__main__.py
chlorine/translate.py
tests/__init__.py
tests/test_translate.py
Chlorine-0.2.13.dist-info/LICENSE
Chlorine-0.2.13.dist-info/METADATA
Chlorine-0.2.13.dist-info/WHEEL
Chlorine-0.2.13.dist-info/top_level.txt
Chlorine-0.2.13.dist-info/RECORD
