Metadata-Version: 2.1
Name: Chlorine
Version: 0.2.13
Summary: The core part of project Fluorine
Home-page: https://www.github.com/rice0208/chlorine
Author: Fluorine Team
Author-email: riceforever0208@outlook.com
License: GPL-3.0 License
Project-URL: Bug Tracker, https://github.com/rice0208
